<?xml version="1.0" encoding="utf-8"?>
<templates id="template" xml:space="preserve">

    <t t-name="weather.WeatherGraphView.Buttons">
        <div class="btn-group" role="toolbar" aria-label="Select location">
            <span class="fs-4 me-2 pt-1">Location:</span>
            <button class="btn btn-secondary bi bi-crosshair o_graph_button" data-tooltip="Use browser location" aria-label="Use browser location" data-mode="browser"
                t-on-click="() => this.onLocationSelected('browser')"
                t-att-class="{ active: model.metaData.location === 'browser' }"
            />
            <button class="btn btn-secondary bi bi-geo-alt o_graph_button" data-tooltip="Use the name of the locality" aria-label="Use the name of the locality" data-mode="locality"
                t-on-click="() => this.onLocationSelected('locality')"
                t-att-class="{ active: model.metaData.location === 'locality' }"
            />
            <input class="locality-name" type="text" name="locality" t-ref="localityInput"
                t-att-value="model.metaData.locality or ''"
                t-if="model.metaData.location === 'locality'"
            />
            <button class="btn btn-secondary bi bi-search o_graph_button" data-tooltip="Search" aria-label="Search" data-mode="search"
                t-on-click="() => this.onSetLocality()"
                t-if="model.metaData.location === 'locality'"
            />
        </div>
        <div class="btn-group" role="toolbar" aria-label="Change forecast parameters">
            <span class="fs-4 ms-2 me-2 pt-1">Period:</span>
            <button class="btn btn-secondary bi bi-cloud-snow o_graph_button" data-tooltip="Now" aria-label="Now" data-mode="now"
                t-on-click="() => this.onPeriodSelected('now')"
                t-att-class="{ active: model.metaData.period === 'now' }"
            />
            <button class="btn btn-secondary bi bi-calendar4-event o_graph_button" data-tooltip="Day" aria-label="Day" data-mode="day"
                t-on-click="() => this.onPeriodSelected('day')"
                t-att-class="{ active: model.metaData.period === 'day' }"
            />
            <button class="btn btn-secondary bi bi-calendar4-week o_graph_button" data-tooltip="Week" aria-label="Week" data-mode="week"
                t-on-click="() => this.onPeriodSelected('week')"
                t-att-class="{ active: model.metaData.period === 'week' }"
            />
        </div>
    </t>

    <t t-name="weather.WeatherGraphRenderer" t-inherit="web.GraphRenderer" t-inherit-mode="primary">
        <xpath expr="//div[@t-ref='container']" position="replace">
            <div class="o_graph_canvas_container flex-grow-1 position-relative px-3 pb-3" t-ref="container">
                <Weather period="model.metaData.period" error="model.metaData.error" title="title" data="state.data" />
            </div>
        </xpath>
    </t>

</templates>
